data_geocoding_utils/__init__.py
data_geocoding_utils/disambiguation.py
data_geocoding_utils/shaping_rules.py
ctk_geocoding_utils-0.0.6.dist-info/LICENCE
ctk_geocoding_utils-0.0.6.dist-info/METADATA
ctk_geocoding_utils-0.0.6.dist-info/WHEEL
ctk_geocoding_utils-0.0.6.dist-info/top_level.txt
ctk_geocoding_utils-0.0.6.dist-info/RECORD
